{
  "company_enc": 0.1784,
  "seniority_enc": 0.1559,
  "city_enc": 0.0736,
  "job_title_enc": 0.0698,
  "experience_years": 0.0441,
  "skill_scala": 0.0438,
  "skill_azure": 0.0415,
  "skill_javascript": 0.0345,
  "skill_css": 0.0269,
  "skill_html": 0.0268,
  "skill_mongodb": 0.0266,
  "skill_aws": 0.0262,
  "skill_mysql": 0.0254,
  "skill_machine_learning": 0.0214,
  "skill_git": 0.0213,
  "skill_excel": 0.0195,
  "company_tier_enc": 0.0181,
  "skill_sql": 0.0179,
  "skill_java": 0.0177,
  "skill_node.js": 0.0166,
  "skill_api": 0.0163,
  "skill_linux": 0.0162,
  "skill_python": 0.0161,
  "skill_react": 0.0159,
  "skill_rest": 0.0155,
  "skill_docker": 0.014
}